btns_menus/Buttons.py
btns_menus/Combinations.py
btns_menus/DropMenus.py
btns_menus/Paginator.py
btns_menus/__init__.py
btns_menus/errors.py
btns_menus/builds/__init__.py
btns_menus/builds/abc.py
btns_menus/builds/button_.py
btns_menus/builds/menu_.py
discord_btns_menus-0.2.6.dist-info/LICENSE
discord_btns_menus-0.2.6.dist-info/METADATA
discord_btns_menus-0.2.6.dist-info/WHEEL
discord_btns_menus-0.2.6.dist-info/top_level.txt
discord_btns_menus-0.2.6.dist-info/RECORD
