Metadata-Version: 2.1
Name: discord-btns-menus
Version: 0.2.6
Summary: A responsive package for Buttons, DropMenus, Combinations and Paginator
Home-page: https://github.com/Modern-Realm/discord_btns_menus
Author: P. Sai Keerthan Reddy
Author-email: saikeerthan.keerthan.9@gmail.com
License: MIT
Project-URL: Documentation, https://modern-realm.github.io/discord_btns_menus/
Project-URL: Bug Tracker, https://github.com/Modern-Realm/discord_btns_menus/issues
Project-URL: Examples, https://github.com/Modern-Realm/discord_btns_menus/tree/main/Examples
Project-URL: Source, https://github.com/Modern-Realm/discord_btns_menus/tree/main/package/btns_menus
Project-URL: Discord Server, https://discord.gg/GVMWx5EaAN
Keywords: py-cord,pycord,buttons,dropmenus,menus,nextcord,disnake,discordpy
Classifier: Development Status :: 5 - Production/Stable
Classifier: Intended Audience :: Developers
Classifier: Programming Language :: Python :: 3.8
Classifier: License :: OSI Approved :: MIT License
Classifier: Operating System :: OS Independent
Classifier: Natural Language :: English
Classifier: Topic :: Internet
Classifier: Topic :: Software Development
Classifier: Topic :: Software Development :: Libraries
Classifier: Topic :: Software Development :: Libraries :: Python Modules
Classifier: Typing :: Typed
Requires-Python: >=3.8
License-File: LICENSE
